hello.py
Teleprompt-0.1.0.dist-info/METADATA
Teleprompt-0.1.0.dist-info/WHEEL
Teleprompt-0.1.0.dist-info/top_level.txt
Teleprompt-0.1.0.dist-info/RECORD
