Metadata-Version: 2.1
Name: Teleprompt
Version: 0.1.0
Summary: Add your description here
Requires-Python: >=3.11
Requires-Dist: dspy-ai >=2.5.28
